{
  "project_info": {
    "project_number": "317219178546",
    "firebase_url": "https://kalrav-165d4.firebaseio.com",
    "project_id": "kalrav-165d4",
    "storage_bucket": "kalrav-165d4.appspot.com"
  },
  "client": [
    {
      "client_info": {
        "mobilesdk_app_id": "1:317219178546:android:fb47a31bb4031952",
        "android_client_info": {
          "package_name": "com.lognsys.kalrav"
        }
      },
      "oauth_client": [
        {
          "client_id": "317219178546-ngl47857ch2cuunvaj274j53b0f0ln7b.apps.googleusercontent.com",
          "client_type": 1,
          "android_info": {
            "package_name": "com.lognsys.kalrav",
            "certificate_hash": "a0938a04a7a3f4c0b3e5745205f8316f53e114c2"
          }
        },
        {
          "client_id": "317219178546-nn4v06t4td6up797cq3gcmjhlj8fjs1e.apps.googleusercontent.com",
          "client_type": 1,
          "android_info": {
            "package_name": "com.lognsys.kalrav",
            "certificate_hash": "3f1834d3a1df93d74253b7176629c473a5c4acdb"
          }
        },
        {
          "client_id": "317219178546-qlokeoi34tgsc9oepue9qtdpa9nseq01.apps.googleusercontent.com",
          "client_type": 3
        }
      ],
      "api_key": [
        {
          "current_key": "AIzaSyAWjz9llvfGuqNMhUTLLV3IvyFaUx37Mes"
        }
      ],
      "services": {
        "analytics_service": {
          "status": 1
        },
        "appinvite_service": {
          "status": 2,
          "other_platform_oauth_client": [
            {
              "client_id": "317219178546-qlokeoi34tgsc9oepue9qtdpa9nseq01.apps.googleusercontent.com",
              "client_type": 3
            }
          ]
        },
        "ads_service": {
          "status": 2
        }
      }
    }
  ],
  "configuration_version": "1"
}